bioread/__init__.py
bioread/_metadata.py
bioread/biopac.py
bioread/data_reader.py
bioread/dtype_header_reader.py
bioread/file_revisions.py
bioread/header_reader.py
bioread/headers.py
bioread/journal_reader.py
bioread/marker_reader.py
bioread/reader.py
bioread/runners/__init__.py
bioread/runners/acq2hdf5.py
bioread/runners/acq2mat.py
bioread/runners/acq2txt.py
bioread/runners/acq_info.py
bioread/runners/acq_layout.py
bioread/runners/acq_markers.py
bioread/writers/__init__.py
bioread/writers/matlabwriter.py
bioread/writers/txtwriter.py
bioread-2025.5.2.dist-info/METADATA
bioread-2025.5.2.dist-info/WHEEL
bioread-2025.5.2.dist-info/entry_points.txt
bioread-2025.5.2.dist-info/licenses/LICENSE
bioread-2025.5.2.dist-info/RECORD
