Metadata-Version: 2.4
Name: bioread
Version: 2025.5.2
Summary: Utilities to read BIOPAC AcqKnowledge files
License-File: LICENSE
Requires-Python: >=3.10
Requires-Dist: docopt>=0.6.1
Requires-Dist: numpy>=2.2.3
Requires-Dist: pytest>=8.3.4
Provides-Extra: all
Requires-Dist: h5py; extra == 'all'
Requires-Dist: scipy; extra == 'all'
Provides-Extra: dev
Requires-Dist: h5py; extra == 'dev'
Requires-Dist: pytest; extra == 'dev'
Requires-Dist: scipy; extra == 'dev'
Provides-Extra: hdf5
Requires-Dist: h5py; extra == 'hdf5'
Provides-Extra: mat
Requires-Dist: scipy; extra == 'mat'
